web_diver/__init__.py
web_diver/diver/__init__.py
web_diver/examples/__init__.py
webdiver-8.0.dist-info/licenses/LICENSE
webdiver-8.0.dist-info/METADATA
webdiver-8.0.dist-info/WHEEL
webdiver-8.0.dist-info/top_level.txt
webdiver-8.0.dist-info/RECORD
