Metadata-Version: 2.4
Name: webdiver
Version: 8.0
Summary: Webdiver for get URI content like text, html, download or DOM TAGs Filter with Scheduling
Home-page: https://github.com/ssmool/webdiver
Author: #asytrick
Author-email: eusmool@gmail.com
Classifier: Programming Language :: Python :: 3
Classifier: Operating System :: OS Independent
Requires-Python: >=3.13.7
License-File: LICENSE
Requires-Dist: requests
Requires-Dist: beautifulsoup4
Dynamic: license-file
